dict_to_db/__init__.py
dict_to_db/_sqlite.py
dict_to_db-0.0.7.dist-info/LICENSE
dict_to_db-0.0.7.dist-info/METADATA
dict_to_db-0.0.7.dist-info/WHEEL
dict_to_db-0.0.7.dist-info/top_level.txt
dict_to_db-0.0.7.dist-info/RECORD
