Metadata-Version: 2.1
Name: dict-to-db
Version: 0.0.7
Summary: 便捷的将dict对象存储到Database[sqlite]中  Conveniently store the dict object in Database[sqlite]
Home-page: https://github.com/wordhui/dict_to_db
Author: poshui
Author-email: poshui@foxmail.com
License: UNKNOWN
Platform: UNKNOWN
Classifier: Development Status :: 4 - Beta
Classifier: Programming Language :: Python :: 3
Classifier: Programming Language :: Python :: 3.6
Classifier: Programming Language :: Python :: 3.7
Classifier: Programming Language :: Python :: 3.8
Classifier: Programming Language :: Python :: 3.9
Classifier: License :: OSI Approved :: MIT License
Classifier: Operating System :: OS Independent
License-File: LICENSE
Requires-Dist: openpyxl
